changelog/ChangeLogMacro.py
changelog/__init__.py
TracChangeLog-0.5.dist-info/COPYING
TracChangeLog-0.5.dist-info/METADATA
TracChangeLog-0.5.dist-info/WHEEL
TracChangeLog-0.5.dist-info/entry_points.txt
TracChangeLog-0.5.dist-info/top_level.txt
TracChangeLog-0.5.dist-info/RECORD
